{
  "_attribution": "Pages from WCXB (murrough-foley/web-content-extraction-benchmark), CC-BY-4.0.",
  "fixtures": [
    {
      "file": "article/4681.html",
      "expectedPageType": "article",
      "domain": "boardgamegeek.com",
      "url": "https://boardgamegeek.com/"
    },
    {
      "file": "article/0488.html",
      "expectedPageType": "article",
      "domain": "hamy.xyz",
      "url": "https://hamy.xyz/"
    },
    {
      "file": "article/0406.html",
      "expectedPageType": "article",
      "domain": "erikdemaine.org",
      "url": "https://erikdemaine.org/"
    },
    {
      "file": "article/4249.html",
      "expectedPageType": "article",
      "domain": "robomow.com",
      "url": "https://robomow.com/"
    },
    {
      "file": "forum/0551.html",
      "expectedPageType": "forum",
      "domain": "",
      "url": "https:///"
    },
    {
      "file": "forum/0541.html",
      "expectedPageType": "forum",
      "domain": "bbs.archlinux.org",
      "url": "https://bbs.archlinux.org/"
    },
    {
      "file": "forum/4802.html",
      "expectedPageType": "forum",
      "domain": "keebtalk.com",
      "url": "https://keebtalk.com/"
    },
    {
      "file": "forum/4278.html",
      "expectedPageType": "forum",
      "domain": "forum.esk8.news",
      "url": "https://forum.esk8.news/"
    },
    {
      "file": "product/4721.html",
      "expectedPageType": "product",
      "domain": "aliexpress.com",
      "url": "https://aliexpress.com/"
    },
    {
      "file": "product/4720.html",
      "expectedPageType": "product",
      "domain": "aliexpress.com",
      "url": "https://aliexpress.com/"
    },
    {
      "file": "product/4722.html",
      "expectedPageType": "product",
      "domain": "aliexpress.com",
      "url": "https://aliexpress.com/"
    },
    {
      "file": "collection/4763.html",
      "expectedPageType": "collection",
      "domain": "buy.glossier.com",
      "url": "https://buy.glossier.com/"
    },
    {
      "file": "collection/4852.html",
      "expectedPageType": "collection",
      "domain": "makersmarket.us",
      "url": "https://makersmarket.us/"
    },
    {
      "file": "collection/4577.html",
      "expectedPageType": "collection",
      "domain": "express.com",
      "url": "https://express.com/"
    },
    {
      "file": "collection/4509.html",
      "expectedPageType": "collection",
      "domain": "peacetarget.com",
      "url": "https://peacetarget.com/"
    },
    {
      "file": "listing/2911.html",
      "expectedPageType": "listing",
      "domain": "news.ycombinator.com",
      "url": "https://news.ycombinator.com/"
    },
    {
      "file": "listing/4788.html",
      "expectedPageType": "listing",
      "domain": "flexispot.com",
      "url": "https://flexispot.com/"
    },
    {
      "file": "listing/4548.html",
      "expectedPageType": "listing",
      "domain": "guides.library.berklee.edu",
      "url": "https://guides.library.berklee.edu/"
    },
    {
      "file": "listing/4532.html",
      "expectedPageType": "listing",
      "domain": "thomasnet.com",
      "url": "https://thomasnet.com/"
    },
    {
      "file": "documentation/4412.html",
      "expectedPageType": "documentation",
      "domain": "docs.aws.amazon.com",
      "url": "https://docs.aws.amazon.com/"
    },
    {
      "file": "documentation/2864.html",
      "expectedPageType": "documentation",
      "domain": "postgresql.org",
      "url": "https://postgresql.org/"
    },
    {
      "file": "documentation/4415.html",
      "expectedPageType": "documentation",
      "domain": "wiki.postgresql.org",
      "url": "https://wiki.postgresql.org/"
    },
    {
      "file": "documentation/2870.html",
      "expectedPageType": "documentation",
      "domain": "nginx.org",
      "url": "https://nginx.org/"
    },
    {
      "file": "service/4871.html",
      "expectedPageType": "service",
      "domain": "cerebral.com",
      "url": "https://cerebral.com/"
    },
    {
      "file": "service/4650.html",
      "expectedPageType": "service",
      "domain": "investor.vanguard.com",
      "url": "https://investor.vanguard.com/"
    },
    {
      "file": "service/4855.html",
      "expectedPageType": "service",
      "domain": "ohioartisancollective.com",
      "url": "https://ohioartisancollective.com/"
    },
    {
      "file": "service/4554.html",
      "expectedPageType": "service",
      "domain": "cityofmarion.in.gov",
      "url": "https://cityofmarion.in.gov/"
    }
  ]
}
